README.rst
setup.py
lcjhello/__init__.py
lcjhello/lcjhello.py
lcjhello.egg-info/PKG-INFO
lcjhello.egg-info/SOURCES.txt
lcjhello.egg-info/dependency_links.txt
lcjhello.egg-info/top_level.txt
lcjhello.egg-info/zip-safe