Metadata-Version: 1.0
Name: lcjhello
Version: 1.0.1
Summary: this is a test package for packing python liberaries tutorial.
Home-page: http://blog.useasp.net/
Author: lcj
Author-email: 123jun460214@163.com
License: MIT
Keywords: test python package
Platform: UNKNOWN
Classifier: License :: OSI Approved :: MIT License
Classifier: Programming Language :: Python
Classifier: Intended Audience :: Developers
Classifier: Operating System :: OS Independent
